napypi-1.0.1.dist-info/WHEEL
napypi-1.0.1.dist-info/METADATA
napypi-1.0.1.dist-info/RECORD
napypi-1.0.1.dist-info/licenses/LICENSE
napypi.libs/libgomp-a34b3233.so.1.0.0
napypi/numba_core.py
napypi/wrapper.py
napypi/__init__.py
napypi/_core.cpython-39-x86_64-linux-gnu.so
