Metadata-Version: 2.1
Name: napypi
Version: 1.0.1
Summary: Efficient statistics in Python for large-scale heterogeneous data with enhanced support for missing data
Author: Fabian Woller
License: GPL-3.0-only
Requires-Python: <3.12,>=3.9
Requires-Dist: torch
Requires-Dist: pandas
Requires-Dist: numba==0.60.0
Requires-Dist: numba-scipy==0.4.0
Requires-Dist: numpy==1.26.*
Requires-Dist: scipy==1.11.0
